base64_to_file/__init__.py
base64_to_file/base64_to_file.py
base64_to_file-0.1.8.dist-info/LICENSE
base64_to_file-0.1.8.dist-info/METADATA
base64_to_file-0.1.8.dist-info/WHEEL
base64_to_file-0.1.8.dist-info/top_level.txt
base64_to_file-0.1.8.dist-info/RECORD
