Metadata-Version: 2.1
Name: base64_to_file
Version: 0.1.8
Summary: A Python package to download file through base64string
Requires-Python: >=3.6
License-File: LICENSE
